pymove_osmnx/__init__.py
pymove_osmnx/_version.py
pymove_osmnx/core/map_matching_osmnx.py
pymove_osmnx/utils/interpolate.py
pymove_osmnx/utils/similarity.py
pymove_osmnx-0.3.0.dist-info/METADATA
pymove_osmnx-0.3.0.dist-info/WHEEL
pymove_osmnx-0.3.0.dist-info/top_level.txt
pymove_osmnx-0.3.0.dist-info/RECORD
