Metadata-Version: 2.1
Name: pymove-osmnx
Version: 0.3.0
Summary: A lib python to integrate PyMove and OSMnx
Home-page: https://github.com/InsightLab/pymove-osmnx
Author: Insight Data Science Lab
Author-email: insightlab@dc.ufc.br
License: MIT
Platform: UNKNOWN
Classifier: Development Status :: 1 - Planning
Classifier: Programming Language :: Python :: 3
Classifier: License :: OSI Approved :: MIT License
Classifier: Operating System :: OS Independent
Requires-Python: >=3.6
Requires-Dist: pymove
Requires-Dist: pandas
Requires-Dist: osmnx
